Metadata-Version: 1.0
Name: probability-dists-ds
Version: 0.1
Summary: Gaussian and Binomial Probability Distributions
Home-page: UNKNOWN
Author: Sunil Raut Kshetri
Author-email: myemail@something.com
License: UNKNOWN
Platform: UNKNOWN
